misho_server/__init__.py
misho_server/alembic.ini
misho_server/alembic/README
misho_server/alembic/env.py
misho_server/alembic/script.py.mako
misho_server/alembic/versions/d9c493bd098f_initial_migration.py
misho_server/config/__init__.py
misho_server/config/dev.py
misho_server/config/model.py
misho_server/config/prod.py
misho_server/controller/__init__.py
misho_server/controller/common.py
misho_server/controller/jobs.py
misho_server/controller/reservation_calendar.py
misho_server/controller/signup.py
misho_server/controller/transformers.py
misho_server/database/__init__.py
misho_server/database/create.py
misho_server/database/migration.py
misho_server/database/model.py
misho_server/domain/__init__.py
misho_server/domain/app_token.py
misho_server/domain/court.py
misho_server/domain/hour_slot.py
misho_server/domain/job.py
misho_server/domain/job_notification.py
misho_server/domain/monitoring_job.py
misho_server/domain/reservation_calendar.py
misho_server/domain/reservation_slot.py
misho_server/domain/session_token.py
misho_server/domain/time_slot.py
misho_server/domain/user.py
misho_server/domain/user_token.py
misho_server/http/auth.py
misho_server/http/http_app.py
misho_server/http/internal_error.py
misho_server/repository/available_job_reservation_slots.py
misho_server/repository/court.py
misho_server/repository/hour_slot.py
misho_server/repository/job_notifications_repository.py
misho_server/repository/jobs.py
misho_server/repository/reservation_calendar.py
misho_server/repository/time_slot.py
misho_server/repository/user.py
misho_server/repository/user_token.py
misho_server/service/job_notifier.py
misho_server/service/mail_service.py
misho_server/service/reservation_monitoring.py
misho_server/service/reservation_scheduler.py
misho_server/service/reservation_service.py
misho_server/service/reserve_job_executor.py
misho_server/service/session_token_fetch_service.py
misho_server/service/sportbooking_service.py
misho_server-0.1.1.dist-info/METADATA
misho_server-0.1.1.dist-info/WHEEL
misho_server-0.1.1.dist-info/entry_points.txt
misho_server-0.1.1.dist-info/RECORD
