Metadata-Version: 2.4
Name: misho-server
Version: 0.1.1
Summary: Add your description here
Author-email: Ivo Petkovic <ivo.petkovic@gmail.com>
Requires-Python: >=3.12
Requires-Dist: aiohttp>=3.12.13
Requires-Dist: aiosmtplib>=4.0.1
Requires-Dist: aiosqlite>=0.21.0
Requires-Dist: alembic>=1.16.1
Requires-Dist: apscheduler>=3.11.0
Requires-Dist: greenlet>=3.2.3
Requires-Dist: misho-api
Requires-Dist: pydantic[email]>=2.11.7
Requires-Dist: sportbooking
Requires-Dist: sqlalchemy>=2.0.41
